ADRINA_STT/__init__.py
ADRINA_STT-0.1.dist-info/METADATA
ADRINA_STT-0.1.dist-info/WHEEL
ADRINA_STT-0.1.dist-info/top_level.txt
ADRINA_STT-0.1.dist-info/RECORD
