Metadata-Version: 2.1
Name: ADRINA_STT
Version: 0.1
Summary: Package
Home-page: https://github.com/adam-dz/package
Author: Anirban
Author-email: a9irba9das@gail.com
